default_config.yml
kb_guardian/__init__.py
kb_guardian/contradiction_detection.py
kb_guardian/docs_chunks_conversion.py
kb_guardian/kb_management.py
kb_guardian/logger.py
kb_guardian/utils/deployment.py
kb_guardian/utils/paths.py
kb_guardian/utils/vectorstore.py
knowledge_base_guardian-0.0.1.dist-info/LICENSE
knowledge_base_guardian-0.0.1.dist-info/METADATA
knowledge_base_guardian-0.0.1.dist-info/WHEEL
knowledge_base_guardian-0.0.1.dist-info/RECORD
