Metadata-Version: 2.1
Name: knowledge-base-guardian
Version: 0.0.1
Summary: An LLM application to safeguard the consistency of documents in a knowledge base
Home-page: https://github.com/datarootsio/knowledgebase_guardian/
License: MIT
Author: Senne Batsleer
Author-email: senne@dataroots.io
Requires-Python: >=3.9,<4.0
Classifier: License :: OSI Approved :: MIT License
Classifier: Programming Language :: Python :: 3
Classifier: Programming Language :: Python :: 3.9
Classifier: Programming Language :: Python :: 3.10
Classifier: Programming Language :: Python :: 3.11
Requires-Dist: bs4 (==0.0.1)
Requires-Dist: faiss-cpu (==1.7.3)
Requires-Dist: langchain (==0.0.213)
Requires-Dist: openai (>=0.27.0,<0.28.0)
Requires-Dist: python-dotenv (==1.0.0)
Requires-Dist: tiktoken (>=0.4.0,<0.5.0)
Requires-Dist: transformers (==4.30.2)
Project-URL: Repository, https://github.com/datarootsio/knowledgebase_guardian/
